django_simplepagination-0.0.1.dist-info/metadata.json
django_simplepagination-0.0.1.dist-info/DESCRIPTION.rst
django_simplepagination-0.0.1.dist-info/top_level.txt
django_simplepagination-0.0.1.dist-info/WHEEL
django_simplepagination-0.0.1.dist-info/RECORD
django_simplepagination-0.0.1.dist-info/METADATA
simplepagination/utils.py
simplepagination/__init__.py
simplepagination/settings.py
simplepagination/backends/filmfeed.py
simplepagination/backends/__init__.py
simplepagination/backends/digg.py
simplepagination/templates/paginator_digg.html
simplepagination/templates/paginator.html
simplepagination/templates/paginator_filmfeed.html
simplepagination/templatetags/__init__.py
simplepagination/templatetags/paginator.py
