Metadata-Version: 2.0
Name: django-simplepagination
Version: 0.0.1
Summary: Django application with multiple type of pagination integrated
Home-page: http://bitbucket.org/offline/django-simplepagination/wiki/
Author: Anderson
Author-email: self.anderson@gmail.com
License: BSD
Keywords: django
Platform: UNKNOWN
Requires-Dist: django-annoying
